tap_hubspot_meister/__init__.py
tap_hubspot_meister/bookmark.py
tap_hubspot_meister/discover.py
tap_hubspot_meister/schemas/companies.json
tap_hubspot_meister/schemas/contacts.json
tap_hubspot_meister/schemas/deals.json
tap_hubspot_meister/state.json
tap_hubspot_meister/streams.py
tap_hubspot_meister/sync.py
tap_hubspot_meister/test/test_associations.py
tap_hubspot_meister/test/test_companies.py
tap_hubspot_meister/test/test_contacts.py
tap_hubspot_meister/test/test_deals.py
tap_hubspot_meister/test/test_hubspot_client.py
tap_hubspot_meister/transform.py
tap_hubspot_meister-0.1.2.dist-info/entry_points.txt
tap_hubspot_meister-0.1.2.dist-info/WHEEL
tap_hubspot_meister-0.1.2.dist-info/METADATA
tap_hubspot_meister-0.1.2.dist-info/RECORD
